[
  {
    "id": "1",
    "title": "Make Pizza",
    "description": "Make a pizza with mozzarella cheese",
    "status": "PENDING",
    "steps": [
      {
        "num": 1,
        "title": "Buy products",
        "status": "PENDING"
      },
      {
        "num": 2,
        "title": "Make the fucking pizza",
        "status": "PENDING"
      },
      {
        "num": 3,
        "title": "Eat this beautiful peace of art",
        "status": "PENDING"
      }
    ]
  },
  {
    "id": "2",
    "title": "Make Pizza 2",
    "description": "",
    "status": "DONE"
  },
  {
    "id": "3",
    "title": "Make Pizza 3",
    "description": "",
    "status": "PENDING",
    "steps": [
      {
        "num": 1,
        "title": "Buy products",
        "status": "PENDING"
      },
      {
        "num": 2,
        "title": "Make the fucking pizza",
        "status": "PENDING"
      },
      {
        "num": 3,
        "title": "Eat this beautiful peace of art",
        "status": "PENDING"
      }
    ]
  },
  {
    "id": "4",
    "title": "Make Pizza 4",
    "status": "DONE",
    "description": "Lorem ipsum dolor sit amet consectetur adipisicing elit. Non officiis adipisci repudiandae natus, quod temporibus unde fugit doloribus omnis fuga nostrum maxime! Animi libero dolor possimus, dolorem eveniet et veritatis explicabo ipsum ratione impedit iste doloribus at consequuntur consectetur rem ipsam maiores voluptatem odit modi accusamus! Asperiores perferendis animi et! Maxime, doloribus quam quisquam, sit consequuntur impedit commodi dicta, voluptatum at omnis ipsum exercitationem neque debitis consequatur voluptatibus velit ullam molestiae animi dolor nemo beatae dolorum expedita. Quisquam accusamus totam numquam nulla officia sit porro quidem, corporis sapiente laborum odio ipsum, odit at, praesentium dolores dolorum delectus itaque suscipit quibusdam!",
    "steps": []
  }
]
